jgtml/AlligatorIllusionDetector.py
jgtml/JGTBalanceAnalyzer.py
jgtml/JGTOutputHelper.py
jgtml/MLFRequest.py
jgtml/SOHelper.py
jgtml/SignalOrderingHelper.py
jgtml/TideAlligatorAnalysis.py
jgtml/__init__.py
jgtml/alligator_cli.py
jgtml/anhelper.py
jgtml/automated_fdb_trading_system.py
jgtml/enhanced_fdb_scanner_with_illusion_detection.py
jgtml/enhanced_trading_cli.py
jgtml/fdb_pattern_intelligence.py
jgtml/fdb_scanner_2408.py
jgtml/fdb_signal_quality_predictor.py
jgtml/jdash.py
jgtml/jgtapp.py
jgtml/jgtml_obsds_240515_TIDE_SIGNALS.py
jgtml/jgtmlcli.py
jgtml/jplt.py
jgtml/jtc.py
jgtml/mfihelper2.py
jgtml/mlclicommon.py
jgtml/mlcliconstants.py
jgtml/mlconstants.py
jgtml/mldatahelper.py
jgtml/mlfcli.py
jgtml/mlfsvc.py
jgtml/mlutils.py
jgtml/mxcli.py
jgtml/mxconstants.py
jgtml/mxhelper.py
jgtml/mxsvc.py
jgtml/pncli.py
jgtml/pto250518.py
jgtml/ptomlf.py
jgtml/ptottf.py
jgtml/ptottfpatterns.py
jgtml/realityhelper.py
jgtml/test_get_files_in_ns.py
jgtml/test_pncli.py
jgtml/test_signal_ordering_helper.py
jgtml/test_soh_gator_validations.py
jgtml/trading_orchestrator.py
jgtml/tst_barhelper_and_pd.py
jgtml/tst_jgtpov.py
jgtml/ttfcli.py
jgtml/ttfsvc.py
jgtml/unified_discovery_dataset_generator.py
jgtml/unified_trading_system.py
jgtml/vertex_ai_data_transformer.py
jgtml/vertex_ai_data_transformer_v2.py
jgtml/xhelper.py
jgtml/zonehelper.py
jgtml-0.0.348.dist-info/licenses/LICENSE
jgtml-0.0.348.dist-info/METADATA
jgtml-0.0.348.dist-info/WHEEL
jgtml-0.0.348.dist-info/entry_points.txt
jgtml-0.0.348.dist-info/top_level.txt
jgtml-0.0.348.dist-info/RECORD
